comm/axisprofile/__init__.py
comm/axisprofile/fbtypes/APRBootState.py
comm/axisprofile/fbtypes/CategoryOfProfile.py
comm/axisprofile/fbtypes/ProfileCategory.py
comm/axisprofile/fbtypes/ProfileType.py
comm/axisprofile/fbtypes/ScalingStrategy.py
comm/axisprofile/fbtypes/__init__.py
comm/axisprofile/fbtypes/deviceScalingType.py
comm/axisprofile/fbtypes/dummyFbs.py
comm/axisprofile/fbtypes/mappingEntry.py
comm/axisprofile/fbtypes/profile.py
comm/axisprofile/fbtypes/profileConfig.py
comm/axisprofile/fbtypes/profileDeviceScalingType.py
comm/axisprofile/fbtypes/profileScalingCfg.py
comm/axisprofile/fbtypes/profileScalingStrategy.py
comm/axisprofile/fbtypes/profileTypeData.py
comm/axisprofile/fbtypes/valueMapping.py
comm/axisprofile/fbtypes/variableType.py
comm/datalayer/AccessType.py
comm/datalayer/Alias.py
comm/datalayer/AliasGroup.py
comm/datalayer/Aliases.py
comm/datalayer/AllowedOperations.py
comm/datalayer/ArrayOfBool8.py
comm/datalayer/ArrayOfDouble.py
comm/datalayer/ArrayOfFloat32.py
comm/datalayer/ArrayOfFloat64.py
comm/datalayer/ArrayOfInt16.py
comm/datalayer/ArrayOfInt32.py
comm/datalayer/ArrayOfInt64.py
comm/datalayer/ArrayOfInt8.py
comm/datalayer/ArrayOfString.py
comm/datalayer/ArrayOfTimestamp.py
comm/datalayer/ArrayOfUInt16.py
comm/datalayer/ArrayOfUInt32.py
comm/datalayer/ArrayOfUInt64.py
comm/datalayer/ArrayOfUInt8.py
comm/datalayer/Bool8.py
comm/datalayer/Capabilities.py
comm/datalayer/ChangeEvents.py
comm/datalayer/CheckOperations.py
comm/datalayer/Claim.py
comm/datalayer/Counting.py
comm/datalayer/DataChangeFilter.py
comm/datalayer/DataChangeTrigger.py
comm/datalayer/DebugChannel.py
comm/datalayer/DiagMoreInfo.py
comm/datalayer/Diagnosis.py
comm/datalayer/DisplayFormat.py
comm/datalayer/Double.py
comm/datalayer/EventInfo.py
comm/datalayer/Extension.py
comm/datalayer/FactoryStats.py
comm/datalayer/FlatcArguments.py
comm/datalayer/Float32.py
comm/datalayer/Float64.py
comm/datalayer/Int16.py
comm/datalayer/Int32.py
comm/datalayer/Int64.py
ctrlx_fbs-2.5.0.dist-info/METADATA
ctrlx_fbs-2.5.0.dist-info/WHEEL
ctrlx_fbs-2.5.0.dist-info/boschrexroth_tac_delivery.txt
ctrlx_fbs-2.5.0.dist-info/top_level.txt
ctrlx_fbs-2.5.0.dist-info/RECORD
