Metadata-Version: 2.1
Name: ctrlx-fbs
Version: 2.5.0
Summary: Python generated fbs
Home-page: https://github.com/boschrexroth/ctrlx-automation-sdk/
Author: Bosch Rexroth AG
Author-email: github@boschrexroth.com
License: UNKNOWN
Platform: linux
Classifier: Programming Language :: Python :: 3.6
Classifier: Operating System :: POSIX :: Linux
Requires-Python: >=3.6
License-File: boschrexroth_tac_delivery.txt
